parmoji/__init__.py
parmoji/core.py
parmoji/helpers.py
parmoji/local_source.py
parmoji/source.py
parmoji-2.0.7.dist-info/METADATA
parmoji-2.0.7.dist-info/WHEEL
parmoji-2.0.7.dist-info/licenses/LICENSE
parmoji-2.0.7.dist-info/RECORD
