Metadata-Version: 2.4
Name: parmoji
Version: 2.0.7
Summary: Pillow-based emoji rendering with HTTP and local sources
Project-URL: Homepage, https://github.com/paulrobello/parmoji
Project-URL: Repository, https://github.com/paulrobello/parmoji
Project-URL: Issues, https://github.com/paulrobello/parmoji/issues
Author-email: Paul Robello <probello@gmail.com>
Maintainer-email: Paul Robello <probello@gmail.com>
License: MIT License
License-File: LICENSE
Keywords: discord,emoji,pillow,renderer,twemoji
Classifier: Development Status :: 4 - Beta
Classifier: Environment :: Console
Classifier: Intended Audience :: Developers
Classifier: License :: OSI Approved :: MIT License
Classifier: Operating System :: MacOS
Classifier: Operating System :: Microsoft :: Windows :: Windows 10
Classifier: Operating System :: Microsoft :: Windows :: Windows 11
Classifier: Operating System :: POSIX :: Linux
Classifier: Programming Language :: Python :: 3
Classifier: Programming Language :: Python :: 3.11
Classifier: Programming Language :: Python :: 3.12
Classifier: Programming Language :: Python :: 3.13
Classifier: Topic :: Multimedia :: Graphics
Classifier: Topic :: Software Development :: Libraries :: Python Modules
Classifier: Typing :: Typed
Requires-Python: >=3.11
Requires-Dist: emoji>=2.14.1
Requires-Dist: httpx>=0.28.1
Requires-Dist: pillow>=11.3.0
Requires-Dist: requests>=2.32.5
Requires-Dist: xdg-base-dirs>=6.0.2
